pymso5000/__init__.py
pymso5000/fetchmso5000.py
pymso5000/mso5000.py
pymso5000_tspspi-0.0.10.dist-info/LICENSE.md
pymso5000_tspspi-0.0.10.dist-info/METADATA
pymso5000_tspspi-0.0.10.dist-info/WHEEL
pymso5000_tspspi-0.0.10.dist-info/entry_points.txt
pymso5000_tspspi-0.0.10.dist-info/top_level.txt
pymso5000_tspspi-0.0.10.dist-info/RECORD
