Metadata-Version: 2.1
Name: pymso5000-tspspi
Version: 0.0.10
Summary: Rigol MSO5000 control library (unofficial)
Home-page: https://github.com/tspspi/pymso5000
Author: Thomas Spielauer
Author-email: pypipackages01@tspi.at
Classifier: Programming Language :: Python :: 3
Classifier: License :: OSI Approved :: BSD License
Classifier: Operating System :: OS Independent
Requires-Python: >=3.6
License-File: LICENSE.md
Requires-Dist: pylabdevs-tspspi >=0.0.11
